gdolim/__init__.py
gdolim-1.1.0.dist-info/LICENSE.txt
gdolim-1.1.0.dist-info/METADATA
gdolim-1.1.0.dist-info/WHEEL
gdolim-1.1.0.dist-info/top_level.txt
gdolim-1.1.0.dist-info/RECORD
