Metadata-Version: 2.1
Name: gdolim
Version: 1.1.0
Summary: Google Spreadsheets Client
Home-page: https://github.com/jossef/gdolim
Author: jossef
Author-email: jossef12@gmail.com
License: Apache v2
Keywords: google,spreadsheets
Platform: UNKNOWN
Requires-Python: >=3.6
License-File: LICENSE.txt
Requires-Dist: google-api-python-client>=2.170.0
Requires-Dist: google-auth-httplib2>=0.2.0
Requires-Dist: google-auth-oauthlib>=1.2.2
Requires-Dist: oauth2client>=4.1.3
Requires-Dist: XlsxWriter>=3.2.3
